tsasync/__init__.py
tsasync/_channel.py
tsasync/_event.py
tsasync/_utils.py
threadsafe_async-0.2.1.dist-info/LICENSE
threadsafe_async-0.2.1.dist-info/METADATA
threadsafe_async-0.2.1.dist-info/WHEEL
threadsafe_async-0.2.1.dist-info/top_level.txt
threadsafe_async-0.2.1.dist-info/RECORD
