Metadata-Version: 2.1
Name: threadsafe-async
Version: 0.2.1
Summary: Thread-safe synchronization primitives
Author-email: Vladimir Perekladov <gleero@gmail.com>
Project-URL: homepage, https://github.com/gleero/python-threadsafe-async
Project-URL: documentation, https://github.com/gleero/python-threadsafe-async/blob/main/README.md
Project-URL: changelog, https://github.com/gleero/python-threadsafe-async/blob/main/CHANGELOG.md
Classifier: Development Status :: 3 - Alpha
Classifier: License :: OSI Approved :: MIT License
Classifier: Natural Language :: English
Classifier: Operating System :: OS Independent
Classifier: Programming Language :: Python
Classifier: Programming Language :: Python :: 3.8
Classifier: Programming Language :: Python :: 3.9
Classifier: Programming Language :: Python :: 3.10
Classifier: Programming Language :: Python :: 3.11
Requires-Python: >=3.8
License-File: LICENSE
Provides-Extra: dev
Requires-Dist: black ==23.3.0 ; extra == 'dev'
Requires-Dist: flake8 ==6.0.0 ; extra == 'dev'
Requires-Dist: Flake8-pyproject ==1.2.3 ; extra == 'dev'
Requires-Dist: isort ==5.12.0 ; extra == 'dev'
Requires-Dist: twine ==4.0.2 ; extra == 'dev'
Requires-Dist: build ==0.10.0 ; extra == 'dev'
Requires-Dist: pre-commit ==3.2.2 ; extra == 'dev'
Provides-Extra: test
Requires-Dist: pytest ==7.3.0 ; extra == 'test'
Requires-Dist: pytest-asyncio ==0.21.0 ; extra == 'test'
Requires-Dist: pytest-cov ==4.0.0 ; extra == 'test'
